hello.py
adsk_ray-0.0.1.dist-info/METADATA
adsk_ray-0.0.1.dist-info/WHEEL
adsk_ray-0.0.1.dist-info/top_level.txt
adsk_ray-0.0.1.dist-info/RECORD
