Metadata-Version: 2.1
Name: adsk-ray
Version: 0.0.1
Summary: adsk package
Requires-Python: >=3.11
